syrinx/__init__.py
syrinx/build.py
syrinx/cli.py
syrinx/exceptions.py
syrinx/preprocess.py
syrinx/read.py
syrinx-0.0.6.dist-info/LICENSE
syrinx-0.0.6.dist-info/METADATA
syrinx-0.0.6.dist-info/WHEEL
syrinx-0.0.6.dist-info/entry_points.txt
syrinx-0.0.6.dist-info/top_level.txt
syrinx-0.0.6.dist-info/RECORD
